ac/__init__.py
ac/core.py
acintellisense-1.1.1.dist-info/LICENSE
acintellisense-1.1.1.dist-info/METADATA
acintellisense-1.1.1.dist-info/WHEEL
acintellisense-1.1.1.dist-info/top_level.txt
acintellisense-1.1.1.dist-info/RECORD
