Metadata-Version: 2.1
Name: acintellisense
Version: 1.1.1
Summary: Assetto Corsa intellisense stubs helper
Author: RipRock
Author-email: <me@riprock.tech>
Keywords: python,AC,Assetto Corsa,dummy,stub
Classifier: Development Status :: 4 - Beta
Classifier: Intended Audience :: Developers
Classifier: Programming Language :: Python :: 3
Classifier: Operating System :: Microsoft :: Windows
Classifier: Topic :: Games/Entertainment :: Simulation
License-File: LICENSE
